th.py
termhand-0.2.1.dist-info/LICENSE
termhand-0.2.1.dist-info/METADATA
termhand-0.2.1.dist-info/WHEEL
termhand-0.2.1.dist-info/entry_points.txt
termhand-0.2.1.dist-info/top_level.txt
termhand-0.2.1.dist-info/RECORD
