Metadata-Version: 2.1
Name: termhand
Version: 0.2.1
Summary: A command-line tool that generates terminal commands from natural language prompts.
Home-page: https://github.com/inclinedadarsh/termhand
Author: Adarsh Dubey
Author-email: dubeyadarshmain@gmail.com
Classifier: Programming Language :: Python :: 3
Classifier: License :: OSI Approved :: MIT License
Classifier: Operating System :: OS Independent
Requires-Python: >=3.6
License-File: LICENSE
Requires-Dist: google-generativeai
